{
  "id": "chatcmpl-Cvlwg2AFvkTN8COV2WXaDQ9EHfzB7",
  "choices": [
    {
      "finish_reason": "stop",
      "index": 0,
      "logprobs": null,
      "message": {
        "content": "```java\npackage com.google.gson.internal;\n\nimport static org.junit.jupiter.api.Assertions.*;\nimport org.junit.jupiter.api.Test;\n\nclass ReflectionAccessFilterHelperTest {\n\n  @Test\n  void testIsAnyPlatformType_withAndroidType() {\n    // Use a real class with name starting with \"android.\"\n    Class<?> fakeAndroidClass = AndroidClass;\n    boolean result = ReflectionAccessFilterHelper.isAnyPlatformType(fakeAndroidClass);\n    assertTrue(result);\n  }\n\n  @Test\n  void testIsAnyPlatformType_withJavaType() {\n    // Java class name starts with \"java.\"\n    Class<?> javaClass = String.class;\n    boolean result = ReflectionAccessFilterHelper.isAnyPlatformType(javaClass);\n    assertTrue(result);\n  }\n\n  @Test\n  void testIsAnyPlatformType_withKotlinType() {\n    Class<?> kotlinClass = KotlinClass;\n    boolean result = ReflectionAccessFilterHelper.isAnyPlatformType(kotlinClass);\n    assertTrue(result);\n  }\n\n  @Test\n  void testIsAnyPlatformType_withKotlinxType() {\n    Class<?> kotlinxClass = KotlinxClass;\n    boolean result = ReflectionAccessFilterHelper.isAnyPlatformType(kotlinxClass);\n    assertTrue(result);\n  }\n\n  @Test\n  void testIsAnyPlatformType_withScalaType() {\n    Class<?> scalaClass = ScalaClass;\n    boolean result = ReflectionAccessFilterHelper.isAnyPlatformType(scalaClass);\n    assertTrue(result);\n  }\n\n  @Test\n  void testIsAnyPlatformType_withNonPlatformType() {\n    Class<?> nonPlatformClass = NonPlatformClass;\n    boolean result = ReflectionAccessFilterHelper.isAnyPlatformType(nonPlatformClass);\n    assertFalse(result);\n  }\n\n  // Helper classes with package-like names by using a custom Class subclass via ProxyClass trick\n  // Since we cannot mock Class, we create wrapper classes with getName() overridden by subclassing ClassLoader\n\n  static class AndroidClass {\n    // We will override getName() via a custom ClassLoader trick below\n  }\n\n  static class KotlinClass {\n  }\n\n  static class KotlinxClass {\n  }\n\n  static class ScalaClass {\n  }\n\n  static class NonPlatformClass {\n  }\n\n  // We cannot change the package of these classes, so we create a utility method to get a Class object\n  // with a fake getName() by using a proxy ClassLoader and define a dummy class with the desired name.\n\n  private static Class<?> createFakeClassWithName(String fakeName) {\n    // Create a dummy class with the desired name by defining a class dynamically with the given name\n    // Using an in-memory class loader\n    try {\n      final String className = fakeName;\n      byte[] classBytes = generateEmptyClassBytes(className);\n      ClassLoader cl = new ClassLoader(ReflectionAccessFilterHelperTest.class.getClassLoader()) {\n        @Override\n        protected Class<?> findClass(String name) throws ClassNotFoundException {\n          if (name.equals(className)) {\n            return defineClass(name, classBytes, 0, classBytes.length);\n          }\n          return super.findClass(name);\n        }\n      };\n      return cl.loadClass(className);\n    } catch (Exception e) {\n      throw new RuntimeException(e);\n    }\n  }\n\n  private static byte[] generateEmptyClassBytes(String className) {\n    // Generate a minimal valid class bytecode with the specified className.\n    // className is fully qualified with dots, need to convert to slashes\n    String internalName = className.replace('.', '/');\n    // Minimal class bytecode generated by ASM or hand-crafted\n    // Here, hardcode a minimal class bytecode for the class:\n    // public class <className> {}\n    // Using ASM is easier, but not allowed here, so use a prebuilt byte array and patch the name.\n\n    // Below is a minimal class bytecode for a public class with no members:\n    byte[] baseClass = new byte[] {\n      (byte)0xCA, (byte)0xFE, (byte)0xBA, (byte)0xBE, // magic\n      0x00, 0x00, 0x00, 0x34, // version 52 (Java 8)\n      0x00, 0x0A, // constant pool count = 10\n      0x07, 0x00, 0x02, // #1 = Class #2\n      0x01, 0x00, 0x10, // #2 = Utf8 \"java/lang/Object\"\n      0x07, 0x00, 0x04, // #3 = Class #4\n      0x01, 0x00, 0x0F, // #4 = Utf8 \"FakeClassName\"\n      0x01, 0x00, 0x06, // #5 = Utf8 \"<init>\"\n      0x01, 0x00, 0x03, // #6 = Utf8 \"()V\"\n      0x01, 0x00, 0x04, // #7 = Utf8 \"Code\"\n      0x0C, 0x00, 0x05, 0x00, 0x06, // #8 = NameAndType #5:#6\n      0x0A, 0x00, 0x01, 0x00, 0x08, // #9 = Methodref #1.#8\n      0x00, 0x21, // access flags: public super\n      0x00, 0x03, // this class #3\n      0x00, 0x01, // super class #1\n      0x00, 0x00, // interfaces count\n      0x00, 0x00, // fields count\n      0x00, 0x01, // methods count\n      0x00, 0x01, // method access flags: public\n      0x00, 0x05, // name index #5 <init>\n      0x00, 0x06, // descriptor index #6 ()V\n      0x00, 0x01, // attributes count\n      0x00, 0x07, // attribute name index #7 Code\n      0x00, 0x00, 0x00, 0x11, // attribute length 17\n      0x00, 0x01, // max stack\n      0x00, 0x01, // max locals\n      0x00, 0x05, // code length\n      0x2A, // aload_0\n      (byte)0xB7, 0x00, 0x09, // invokespecial #9\n      (byte)0xB1, // return\n      0x00, 0x00, // exception table length\n      0x00, 0x00, // attributes count\n      0x00, 0x00 // end\n    };\n\n    // Patch the Utf8 constant #4 \"FakeClassName\" with the correct internalName\n    // The Utf8 length is 15 (0x0F), we need to replace \"FakeClassName\" with internalName and pad if shorter\n\n    byte[] nameBytes = internalName.getBytes();\n    if (nameBytes.length > 15) {\n      throw new IllegalArgumentException(\"Class name too long for this minimal class generator\");\n    }\n\n    baseClass[19] = (byte) nameBytes.length; // length byte for Utf8\n\n    System.arraycopy(nameBytes, 0, baseClass, 20, nameBytes.length);\n\n    // If shorter than 15, pad with zeros\n    for (int i = 20 + nameBytes.length; i < 20 + 15; i++) {\n      baseClass[i] = 0;\n    }\n\n    return baseClass;\n  }\n\n  // Replace the classes with fake classes with proper names\n\n  private static final Class<?> AndroidClass = createFakeClassWithName(\"android.app.Activity\");\n  private static final Class<?> KotlinClass = createFakeClassWithName(\"kotlin.DummyKotlin\");\n  private static final Class<?> KotlinxClass = createFakeClassWithName(\"kotlinx.DummyKotlinx\");\n  private static final Class<?> ScalaClass = createFakeClassWithName(\"scala.DummyScala\");\n  private static final Class<?> NonPlatformClass = createFakeClassWithName(\"dummy.NonPlatform\");\n}\n```",
        "refusal": null,
        "role": "assistant",
        "annotations": [],
        "audio": null,
        "function_call": null,
        "tool_calls": null
      }
    }
  ],
  "created": 1767885034,
  "model": "gpt-4.1-mini-2025-04-14",
  "object": "chat.completion",
  "service_tier": null,
  "system_fingerprint": "fp_3dcd5944f5",
  "usage": {
    "completion_tokens": 1814,
    "prompt_tokens": 2243,
    "total_tokens": 4057,
    "completion_tokens_details": {
      "accepted_prediction_tokens": 0,
      "audio_tokens": 0,
      "reasoning_tokens": 0,
      "rejected_prediction_tokens": 0
    },
    "prompt_tokens_details": {
      "audio_tokens": 0,
      "cached_tokens": 0
    },
    "llm_elapsed_time_seconds": 143.82
  }
}