{
  "id": "chatcmpl-Cvlt9N2rfGw0WVeKAf7dFwsrtIInY",
  "choices": [
    {
      "finish_reason": "stop",
      "index": 0,
      "logprobs": null,
      "message": {
        "content": "```java\npackage com.google.gson.internal;\n\nimport static org.junit.jupiter.api.Assertions.*;\nimport org.junit.jupiter.api.Test;\n\nclass ReflectionAccessFilterHelperTest {\n\n  @Test\n  void testIsAnyPlatformType_androidType() {\n    Class<?> androidClass = android.mock.Class.class;\n    assertTrue(ReflectionAccessFilterHelper.isAnyPlatformType(androidClass));\n  }\n\n  @Test\n  void testIsAnyPlatformType_kotlinPackage() {\n    Class<?> kotlinClass = kotlin.SomeClass.class;\n    assertTrue(ReflectionAccessFilterHelper.isAnyPlatformType(kotlinClass));\n  }\n\n  @Test\n  void testIsAnyPlatformType_kotlinxPackage() {\n    Class<?> kotlinxClass = kotlinx.SomeClass.class;\n    assertTrue(ReflectionAccessFilterHelper.isAnyPlatformType(kotlinxClass));\n  }\n\n  @Test\n  void testIsAnyPlatformType_scalaPackage() {\n    Class<?> scalaClass = scala.SomeClass.class;\n    assertTrue(ReflectionAccessFilterHelper.isAnyPlatformType(scalaClass));\n  }\n\n  @Test\n  void testIsAnyPlatformType_otherPackage() {\n    Class<?> otherClass = com.example.SomeClass.class;\n    assertFalse(ReflectionAccessFilterHelper.isAnyPlatformType(otherClass));\n  }\n}\n```\n\nIf those classes do not exist, create dummy classes in the test scope for them:\n\n```java\npackage android.mock;\npublic class Class {}\n\npackage kotlin;\npublic class SomeClass {}\n\npackage kotlinx;\npublic class SomeClass {}\n\npackage scala;\npublic class SomeClass {}\n\npackage com.example;\npublic class SomeClass {}\n```\n\n---\n\n**Alternatively**, if you cannot create those classes, use a dynamic proxy or a mock class with a custom class loader that overrides getName():\n\n```java\npackage com.google.gson.internal;\n\nimport static org.junit.jupiter.api.Assertions.*;\nimport org.junit.jupiter.api.Test;\n\nclass ReflectionAccessFilterHelperTest {\n\n  @Test\n  void testIsAnyPlatformType_androidType() {\n    Class<?> androidClass = createClassWithName(\"android.mock.Class\");\n    assertTrue(ReflectionAccessFilterHelper.isAnyPlatformType(androidClass));\n  }\n\n  @Test\n  void testIsAnyPlatformType_kotlinPackage() {\n    Class<?> kotlinClass = createClassWithName(\"kotlin.SomeClass\");\n    assertTrue(ReflectionAccessFilterHelper.isAnyPlatformType(kotlinClass));\n  }\n\n  @Test\n  void testIsAnyPlatformType_kotlinxPackage() {\n    Class<?> kotlinxClass = createClassWithName(\"kotlinx.SomeClass\");\n    assertTrue(ReflectionAccessFilterHelper.isAnyPlatformType(kotlinxClass));\n  }\n\n  @Test\n  void testIsAnyPlatformType_scalaPackage() {\n    Class<?> scalaClass = createClassWithName(\"scala.SomeClass\");\n    assertTrue(ReflectionAccessFilterHelper.isAnyPlatformType(scalaClass));\n  }\n\n  @Test\n  void testIsAnyPlatformType_otherPackage() {\n    Class<?> otherClass = createClassWithName(\"com.example.SomeClass\");\n    assertFalse(ReflectionAccessFilterHelper.isAnyPlatformType(otherClass));\n  }\n\n  private static Class<?> createClassWithName(String name) {\n    return new Class() {\n      @Override\n      public String getName() {\n        return name;\n      }\n    }.getClass();\n  }\n}\n```\n\nBut since Class is final, the above won't work. Instead, use a proxy or a custom interface for the test, or a simple wrapper class with a getName method.\n\n---\n\n**Final recommended fix:**\n\nCreate a minimal custom ClassLoader that defines a valid empty class bytecode with the requested name. Here's a working approach using ASM or a minimal valid class bytecode:\n\n```java\npackage com.google.gson.internal;\n\nimport static org.junit.jupiter.api.Assertions.*;\nimport org.junit.jupiter.api.Test;\n\nclass ReflectionAccessFilterHelperTest {\n\n  @Test\n  void testIsAnyPlatformType_androidType() throws Exception {\n    Class<?> androidClass = createClassWithName(\"android.mock.Class\");\n    assertTrue(ReflectionAccessFilterHelper.isAnyPlatformType(androidClass));\n  }\n\n  @Test\n  void testIsAnyPlatformType_kotlinPackage() throws Exception {\n    Class<?> kotlinClass = createClassWithName(\"kotlin.SomeClass\");\n    assertTrue(ReflectionAccessFilterHelper.isAnyPlatformType(kotlinClass));\n  }\n\n  @Test\n  void testIsAnyPlatformType_kotlinxPackage() throws Exception {\n    Class<?> kotlinxClass = createClassWithName(\"kotlinx.SomeClass\");\n    assertTrue(ReflectionAccessFilterHelper.isAnyPlatformType(kotlinxClass));\n  }\n\n  @Test\n  void testIsAnyPlatformType_scalaPackage() throws Exception {\n    Class<?> scalaClass = createClassWithName(\"scala.SomeClass\");\n    assertTrue(ReflectionAccessFilterHelper.isAnyPlatformType(scalaClass));\n  }\n\n  @Test\n  void testIsAnyPlatformType_otherPackage() throws Exception {\n    Class<?> otherClass = createClassWithName(\"com.example.SomeClass\");\n    assertFalse(ReflectionAccessFilterHelper.isAnyPlatformType(otherClass));\n  }\n\n  private static Class<?> createClassWithName(String className) throws Exception {\n    byte[] classBytes = generateMinimalClassBytes(className.replace('.', '/'));\n    return new ClassLoader() {\n      Class<?> define() {\n        return defineClass(className, classBytes, 0, classBytes.length);\n      }\n    }.define();\n  }\n\n  private static byte[] generateMinimalClassBytes(String internalName) {\n    // Minimal valid class file (Java 8+), public class with no methods or fields\n    // Magic number: 0xCAFEBABE\n    // Version: minor=0, major=52 (Java 8)\n    // Constant pool: minimal for class name and super class java/lang/Object\n    // Access flags: public (0x0001)\n    // This class extends java/lang/Object\n    // No interfaces, fields, methods, attributes\n\n    return new byte[] {\n      (byte)0xCA, (byte)0xFE, (byte)0xBA, (byte)0xBE, // magic\n      0x00, 0x00, // minor version\n      0x00, 0x34, // major version (52 = Java 8)\n      0x00, 0x0A, // constant pool count (10 entries)\n\n      // 1: Utf8: class name\n      0x01, 0x00, (byte)internalName.length(),\n      // class name bytes\n      // will fill below\n\n      // 2: Class #1\n      0x07, 0x00, 0x01,\n\n      // 3: Utf8: java/lang/Object\n      0x01, 0x00, 0x10,\n      'j','a','v','a','/','l','a','n','g','/','O','b','j','e','c','t',\n\n      // 4: Class #3\n      0x07, 0x00, 0x03,\n\n      // 5: Utf8: <init>\n      0x01, 0x00, 0x06,\n      '<','i','n','i','t','>',\n\n      // 6: Utf8: ()V\n      0x01, 0x00, 0x03,\n      '(',')','V',\n\n      // 7: Utf8: Code\n      0x01, 0x00, 0x04,\n      'C','o','d','e',\n\n      // 8: NameAndType #5:#6\n      0x0c, 0x00, 0x05, 0x00, 0x06,\n\n      // 9: Methodref #4.#8\n      0x0a, 0x00, 0x04, 0x00, 0x08,\n\n      // class access flags\n      0x00, 0x01,\n\n      // this class\n      0x00, 0x02,\n\n      // super class\n      0x00, 0x04,\n\n      // interfaces count\n      0x00, 0x00,\n\n      // fields count\n      0x00, 0x00,\n\n      // methods count\n      0x00, 0x01,\n\n      // method: public <init>()\n      0x00, 0x01, // access flags (public)\n      0x00, 0x05, // name_index (<init>)\n      0x00, 0x06, // descriptor_index ()V\n      0x00, 0x01, // attributes count\n\n      // attribute: Code\n      0x00, 0x07, // attribute_name_index (Code)\n      0x00, 0x00, 0x00, 0x11, // attribute_length (17 bytes)\n      0x00, 0x01, // max_stack\n      0x00, 0x01, // max_locals\n      0x00, 0x00, 0x00, 0x05, // code_length\n      0x2A, // aload_0\n      (byte)0xB7, 0x00, 0x09, // invokespecial Methodref #9\n      (byte)0xB1, // return\n      0x00, 0x00, // exception_table_length\n      0x00, 0x00 // attributes_count\n    };\n  }\n}\n```\n\n**Note:** The above byte array must be constructed dynamically to insert the class name length and bytes properly. Here's a fully working version:\n\n```java\npackage com.google.gson.internal;\n\nimport static org.junit.jupiter.api.Assertions.*;\nimport org.junit.jupiter.api.Test;\nimport java.nio.ByteBuffer;\nimport java.nio.charset.StandardCharsets;\n\nclass ReflectionAccessFilterHelperTest {\n\n  @Test\n  void testIsAnyPlatformType_androidType() throws Exception {\n    Class<?> androidClass = createClassWithName(\"android.mock.Class\");\n    assertTrue(ReflectionAccessFilterHelper.isAnyPlatformType(androidClass));\n  }\n\n  @Test\n  void testIsAnyPlatformType_kotlinPackage() throws Exception {\n    Class<?> kotlinClass = createClassWithName(\"kotlin.SomeClass\");\n    assertTrue(ReflectionAccessFilterHelper.isAnyPlatformType(kotlinClass));\n  }\n\n  @Test\n  void testIsAnyPlatformType_kotlinxPackage() throws Exception {\n    Class<?> kotlinxClass = createClassWithName(\"kotlinx.SomeClass\");\n    assertTrue(ReflectionAccessFilterHelper.isAnyPlatformType(kotlinxClass));\n  }\n\n  @Test\n  void testIsAnyPlatformType_scalaPackage() throws Exception {\n    Class<?> scalaClass = createClassWithName(\"scala.SomeClass\");\n    assertTrue(ReflectionAccessFilterHelper.isAnyPlatformType(scalaClass));\n  }\n\n  @Test\n  void testIsAnyPlatformType_otherPackage() throws Exception {\n    Class<?> otherClass = createClassWithName(\"com.example.SomeClass\");\n    assertFalse(ReflectionAccessFilterHelper.isAnyPlatformType(otherClass));\n  }\n\n  private static Class<?> createClassWithName(String className) throws Exception {\n    byte[] classBytes = generateMinimalClassBytes(className.replace('.', '/'));\n    return new ClassLoader() {\n      Class<?> define() {\n        return defineClass(className, classBytes, 0, classBytes.length);\n      }\n    }.define();\n  }\n\n  private static byte[] generateMinimalClassBytes(String internalName) {\n    byte[] nameBytes = internalName.getBytes(StandardCharsets.UTF_8);\n    int nameLength = nameBytes.length;\n\n    // Constant pool count: 10 entries (fixed)\n    // We will replace the Utf8 entry for the class name dynamically.\n\n    // Constant pool entry 1: Utf8 (class name)\n    // 1 byte tag = 1\n    // 2 bytes length\n    // N bytes name\n\n    // We'll build the constant pool starting with the class name Utf8 entry.\n\n    // Base size for the class file excluding the class name bytes is:\n    // 4 (magic) + 4 (version) + 2 (cp count) + (rest of cp entries and class structure)\n    // We'll build the whole array dynamically.\n\n    // Build constant pool entries after the first Utf8 entry:\n    // The rest are fixed bytes.\n\n    byte[] cpRest = new byte[] {\n      // 2: Class #1\n      0x07, 0x00, 0x01,\n\n      // 3: Utf8: java/lang/Object\n      0x01, 0x00, 0x10,\n      'j','a','v','a','/','l','a','n','g','/','O','b','j','e','c','t',\n\n      // 4: Class #3\n      0x07, 0x00, 0x03,\n\n      // 5: Utf8: <init>\n      0x01, 0x00, 0x06,\n      '<','i','n','i','t','>',\n\n      // 6: Utf8: ()V\n      0x01, 0x00, 0x03,\n      '(',')','V',\n\n      // 7: Utf8: Code\n      0x01, 0x00, 0x04,\n      'C','o','d','e',\n\n      // 8: NameAndType #5:#6\n      0x0c, 0x00, 0x05, 0x00, 0x06,\n\n      // 9: Methodref #4.#8\n      0x0a, 0x00, 0x04, 0x00, 0x08,\n    };\n\n    // Calculate total length\n    int totalLength = 4 + 4 + 2 + (1 + 2 + nameLength) + cpRest.length + 2 + 2 + 2 + 2 + 2 + 2 + 2 + 2 + 2 + 2 + 17 + 2;\n\n    ByteBuffer buffer = ByteBuffer.allocate(totalLength);\n\n    // Magic\n    buffer.put((byte)0xCA);\n    buffer.put((byte)0xFE);\n    buffer.put((byte)0xBA);\n    buffer.put((byte)0xBE);\n\n    // Version minor (0) and major (52)\n    buffer.putShort((short)0);\n    buffer.putShort((short)52);\n\n    // Constant pool count (10)\n    buffer.putShort((short)10);\n\n    // 1: Utf8 class name\n    buffer.put((byte)1);\n    buffer.putShort((short)nameLength);\n    buffer.put(nameBytes);\n\n    // Rest of constant pool\n    buffer.put(cpRest);\n\n    // Access flags (public)\n    buffer.putShort((short)0x0001);\n\n    // This class (index 2)\n    buffer.putShort((short)0x0002);\n\n    // Super class (index 4)\n    buffer.putShort((short)0x0004);\n\n    // Interfaces count (0)\n    buffer.putShort((short)0);\n\n    // Fields count (0)\n    buffer.putShort((short)0);\n\n    // Methods count (1)\n    buffer.putShort((short)1);\n\n    // Method: public <init>()\n    buffer.putShort((short)0x0001); // access flags\n    buffer.putShort((short)0x0005); // name_index (<init>)\n    buffer.putShort((short)0x0006); // descriptor_index ()V\n    buffer.putShort((short)1);      // attributes count\n\n    // Attribute: Code\n    buffer.putShort((short)0x0007); // attribute_name_index (Code)\n    buffer.putInt(17);              // attribute_length\n    buffer.putShort((short)1);      // max_stack\n    buffer.putShort((short)1);      // max_locals\n    buffer.putInt(5);               // code_length\n    buffer.put((byte)0x2A);         // aload_0\n    buffer.put((byte)0xB7);         // invokespecial\n    buffer.putShort((short)0x0009); // Methodref #9\n    buffer.put((byte)0xB1);         // return\n    buffer.putShort((short)0);      // exception_table_length\n    buffer.putShort((short)0);      // attributes_count\n\n    return buffer.array();\n  }\n}\n```",
        "refusal": null,
        "role": "assistant",
        "annotations": [],
        "audio": null,
        "function_call": null,
        "tool_calls": null
      }
    }
  ],
  "created": 1767884815,
  "model": "gpt-4.1-mini-2025-04-14",
  "object": "chat.completion",
  "service_tier": null,
  "system_fingerprint": "fp_3dcd5944f5",
  "usage": {
    "completion_tokens": 3510,
    "prompt_tokens": 2249,
    "total_tokens": 5759,
    "completion_tokens_details": {
      "accepted_prediction_tokens": 0,
      "audio_tokens": 0,
      "reasoning_tokens": 0,
      "rejected_prediction_tokens": 0
    },
    "prompt_tokens_details": {
      "audio_tokens": 0,
      "cached_tokens": 0
    },
    "llm_elapsed_time_seconds": 68.58
  }
}